{
  "hero": {
    "is_player": true, "sn": "我",
    "base_stats": {
      "limbs": { "head": 35, "chest": 75, "stomach": 50, "l_arm": 60, "r_arm": 60, "l_leg": 60, "r_leg": 60 },
      "maxLimbs": { "head": 35, "chest": 75, "stomach": 50, "l_arm": 60, "r_arm": 60, "l_leg": 60, "r_leg": 60 },
      "fullness": 100, "hydration": 100, "fatigue": 0, "buffs": []
    }
  },
  "old_man": {
    "sn": "老者",
    "fn": "白发苍苍的神秘老者",
    "type": "npc",
    "acts": [
      {
        "id": "event_old_man_snort",
        "label": "对话",
        "repeatable": false,
        "event_type": "type_dialogue",
        "cmd": [
          { "type": "log", "val": "你试图搭话，老者只是冷哼一声：‘哼！’，随后便不再理你。" }
        ]
      }
    ]
  }
}